{"id":"badgeCreations","type":"data","data":{"toggleExplorer":{"created":1742823549343},"switchTheme":{"created":1742823570183},"toggleSideBar":{"created":1742823577607},"exportHtml":{"created":1742823593528},"createFile":{"created":1742823970221},"switchFile":{"created":1742823970232},"githubSyncMainWorkspace":{"created":1742823987837},"triggerSync":{"created":1742824065183},"renameFile":{"created":1742824119109},"createFolder":{"created":1742824898443},"toggleSidePreview":{"created":1742834248299},"toggleNavigationBar":{"created":1742834252762},"toggleEditor":{"created":1742834259586},"renameFolder":{"created":1742834601065},"toggleStatusBar":{"created":1742834882955},"toggleScrollSync":{"created":1742834885587},"removeFolder":{"created":1742835000531},"importMarkdown":{"created":1742835271052},"moveFile":{"created":1742835281685},"removeFile":{"created":1742835392500},"formatButtons":{"created":1743508851915},"exportMarkdown":{"created":1743512053111},"exportPdf":{"created":1762952365406},"removeAccount":{"created":1766405539194}},"hash":-1229087909}